dronekit_sitl/__init__.py
dronekit_sitl/__main__.py
dronekit_sitl/forwarder.py
dronekit_sitl/pysim/aircraft.py
dronekit_sitl/pysim/crrcsim.py
dronekit_sitl/pysim/fdpexpect.py
dronekit_sitl/pysim/fg_display.py
dronekit_sitl/pysim/gimbal.py
dronekit_sitl/pysim/helicopter.py
dronekit_sitl/pysim/iris_ros.py
dronekit_sitl/pysim/multicopter.py
dronekit_sitl/pysim/rotmat.py
dronekit_sitl/pysim/rover.py
dronekit_sitl/pysim/sim_tracker.py
dronekit_sitl/pysim/sim_wrapper.py
dronekit_sitl/pysim/testwind.py
dronekit_sitl/pysim/tracker.py
dronekit_sitl/pysim/util.py
dronekit_sitl-3.3.0.dist-info/METADATA
dronekit_sitl-3.3.0.dist-info/WHEEL
dronekit_sitl-3.3.0.dist-info/entry_points.txt
dronekit_sitl-3.3.0.dist-info/top_level.txt
dronekit_sitl-3.3.0.dist-info/RECORD
