Metadata-Version: 1.0
Name: dronekit_sitl
Version: 3.3.0
Summary: DroneKit library to run SITL (simulation environment)
Home-page: https://github.com/dronekit/dronekit-sitl/
Author: Tim Ryan
Author-email: tim@3drobotics.com
License: UNKNOWN
Platform: UNKNOWN
